couchbase_streamlit_connector/__about__.py
couchbase_streamlit_connector/__init__.py
couchbase_streamlit_connector/connector.py
couchbase_streamlit_connector-0.2.6.dist-info/METADATA
couchbase_streamlit_connector-0.2.6.dist-info/WHEEL
couchbase_streamlit_connector-0.2.6.dist-info/licenses/LICENSE
couchbase_streamlit_connector-0.2.6.dist-info/RECORD
