Metadata-Version: 2.4
Name: couchbase-streamlit-connector
Version: 0.2.6
Summary: Connector for Couchbase on Streamlit
Project-URL: Documentation, https://github.com/Couchbase-Ecosystem/couchbase-streamlit-connector#readme
Project-URL: Issues, https://github.com/Couchbase-Ecosystem/couchbase-streamlit-connector/issues
Project-URL: Source, https://github.com/Couchbase-Ecosystem/couchbase-streamlit-connector
Author-email: Viraj Agarwal <virajagarwal15@gmail.com>
License:                                  Apache License
License-File: LICENSE
Keywords: connector,couchbase,couchbase-connector,couchbase-streamlit-connector,streamlit,streamlit-connector
Classifier: Development Status :: 4 - Beta
Classifier: Programming Language :: Python
Classifier: Programming Language :: Python :: 3.8
Classifier: Programming Language :: Python :: 3.9
Classifier: Programming Language :: Python :: 3.10
Classifier: Programming Language :: Python :: 3.11
Classifier: Programming Language :: Python :: 3.12
Classifier: Programming Language :: Python :: Implementation :: CPython
Classifier: Programming Language :: Python :: Implementation :: PyPy
Requires-Python: >=3.10
Requires-Dist: couchbase
Requires-Dist: streamlit
